letsrobot_unofficial/ChatServerInbound.py
letsrobot_unofficial/ControlServerInbound.py
letsrobot_unofficial/LetsRobot.py
letsrobot_unofficial/PremadeCommands.py
letsrobot_unofficial/ServerHelper.py
letsrobot_unofficial/VideoServerOutbound.py
letsrobot_unofficial/VideoSettings.py
letsrobot_unofficial/__init__.py
letsrobot_unofficial-0.1.5.dist-info/METADATA
letsrobot_unofficial-0.1.5.dist-info/RECORD
letsrobot_unofficial-0.1.5.dist-info/WHEEL
letsrobot_unofficial-0.1.5.dist-info/top_level.txt
