Metadata-Version: 2.1
Name: letsrobot-unofficial
Version: 0.1.5
Summary: Library to interface with LetsRobot
Home-page: https://github.com/theodorechandler1/LetsRobotUnofficial
Author: Theodore Chandler
Author-email: theodorechandler1+LetsRobot@gmail.com
License: LICENSE.txt
Platform: UNKNOWN
Requires-Dist: socketIO-client
